RouteAirPollEstimator/RouteAirPollEstimator.py
RouteAirPollEstimator/__init__.py
RouteAirPollEstimator/sampleData/AirPollutantSurface/fishnet_100m_4_16_07h.cpg
RouteAirPollEstimator/sampleData/AirPollutantSurface/fishnet_100m_4_16_07h.dbf
RouteAirPollEstimator/sampleData/AirPollutantSurface/fishnet_100m_4_16_07h.prj
RouteAirPollEstimator/sampleData/AirPollutantSurface/fishnet_100m_4_16_07h.shp
RouteAirPollEstimator/sampleData/AirPollutantSurface/fishnet_100m_4_16_07h.shp.xml
RouteAirPollEstimator/sampleData/AirPollutantSurface/fishnet_100m_4_16_07h.shx
RouteAirPollEstimator/sampleData/AirPollutantSurface/fishnet_100m_4_16_08h.cpg
RouteAirPollEstimator/sampleData/AirPollutantSurface/fishnet_100m_4_16_08h.dbf
RouteAirPollEstimator/sampleData/AirPollutantSurface/fishnet_100m_4_16_08h.prj
RouteAirPollEstimator/sampleData/AirPollutantSurface/fishnet_100m_4_16_08h.shp
RouteAirPollEstimator/sampleData/AirPollutantSurface/fishnet_100m_4_16_08h.shp.xml
RouteAirPollEstimator/sampleData/AirPollutantSurface/fishnet_100m_4_16_08h.shx
RouteAirPollEstimator/sampleData/AirPollutantSurface/fishnet_100m_4_16_09h.cpg
RouteAirPollEstimator/sampleData/AirPollutantSurface/fishnet_100m_4_16_09h.dbf
RouteAirPollEstimator/sampleData/AirPollutantSurface/fishnet_100m_4_16_09h.prj
RouteAirPollEstimator/sampleData/AirPollutantSurface/fishnet_100m_4_16_09h.shp
RouteAirPollEstimator/sampleData/AirPollutantSurface/fishnet_100m_4_16_09h.shp.xml
RouteAirPollEstimator/sampleData/AirPollutantSurface/fishnet_100m_4_16_09h.shx
RouteAirPollEstimator/sampleData/bicy_rental_loc/bicy_rental_loc.cpg
RouteAirPollEstimator/sampleData/bicy_rental_loc/bicy_rental_loc.dbf
RouteAirPollEstimator/sampleData/bicy_rental_loc/bicy_rental_loc.prj
RouteAirPollEstimator/sampleData/bicy_rental_loc/bicy_rental_loc.sbn
RouteAirPollEstimator/sampleData/bicy_rental_loc/bicy_rental_loc.sbx
RouteAirPollEstimator/sampleData/bicy_rental_loc/bicy_rental_loc.shp
RouteAirPollEstimator/sampleData/bicy_rental_loc/bicy_rental_loc.shx
RouteAirPollEstimator-0.0.2.dist-info/METADATA
RouteAirPollEstimator-0.0.2.dist-info/WHEEL
RouteAirPollEstimator-0.0.2.dist-info/top_level.txt
RouteAirPollEstimator-0.0.2.dist-info/RECORD
