Metadata-Version: 2.1
Name: RouteAirPollEstimator
Version: 0.0.2
Summary: A library for estimating spatial-temporal air pollution exposure amounts by dividing routes.
Home-page: https://github.com/MG-Choi/RouteAirPollEstimator
Author: MoongiChoi
Author-email: u1316663@utah.edu
License: UNKNOWN
Platform: UNKNOWN
Requires-Dist: numpy
Requires-Dist: pandas
Requires-Dist: geopandas (>=0.14)
Requires-Dist: tqdm
Requires-Dist: shapely
